iexcloud/__init__.py
iexcloud/_version.py
iexcloud/config.py
iexcloud/constants.py
iexcloud/reference.py
iexcloud/stock.py
iexcloud-0.0.1.dist-info/LICENSE
iexcloud-0.0.1.dist-info/METADATA
iexcloud-0.0.1.dist-info/WHEEL
iexcloud-0.0.1.dist-info/top_level.txt
iexcloud-0.0.1.dist-info/RECORD
